cytaxii2/__init__.py
cytaxii2/cytaxii2.py
cytaxii2-1.0.1.dist-info/licenses/LICENSE
cytaxii2-1.0.1.dist-info/METADATA
cytaxii2-1.0.1.dist-info/WHEEL
cytaxii2-1.0.1.dist-info/top_level.txt
cytaxii2-1.0.1.dist-info/RECORD
