Metadata-Version: 2.4
Name: cytaxii2
Version: 1.0.1
Summary: This python package is created by Cyware Labs, as a TAXII 2 Client. This can be used easily by developers to connect to a TAXII 2 Server and perform actions
Home-page: https://github.com/cyware-labs/cytaxii2
Author: Cyware Labs
Author-email: contact@cyware.com
License: MIT License
Classifier: Intended Audience :: Information Technology
Classifier: Intended Audience :: Developers
Classifier: License :: OSI Approved :: MIT License
Classifier: Programming Language :: Python :: 3
Classifier: Programming Language :: Python :: 3.4
Classifier: Programming Language :: Python :: 3.5
Classifier: Programming Language :: Python :: 3.6
Classifier: Programming Language :: Python :: 3.7
Classifier: Programming Language :: Python :: 3.8
Classifier: Programming Language :: Python :: 3.9
License-File: LICENSE
Requires-Dist: requests
Dynamic: author
Dynamic: author-email
Dynamic: classifier
Dynamic: description
Dynamic: description-content-type
Dynamic: home-page
Dynamic: license
Dynamic: license-file
Dynamic: requires-dist
Dynamic: summary
